ldp/__init__.py
ldp/data_structures.py
ldp/main.py
ldp/py.typed
ldp/shims.py
ldp/utils.py
ldp/version.py
ldp/agent/__init__.py
ldp/agent/agent.py
ldp/agent/agent_client.py
ldp/agent/interactive_agent.py
ldp/agent/memory_agent.py
ldp/agent/react_agent.py
ldp/agent/simple_agent.py
ldp/agent/tree_of_thoughts_agent.py
ldp/alg/__init__.py
ldp/alg/algorithms.py
ldp/alg/beam_search.py
ldp/alg/callbacks.py
ldp/alg/datasets.py
ldp/alg/rollout.py
ldp/alg/runners.py
ldp/alg/tree_search.py
ldp/alg/optimizer/__init__.py
ldp/alg/optimizer/ape.py
ldp/alg/optimizer/memory.py
ldp/alg/optimizer/opt.py
ldp/alg/optimizer/replay_buffers.py
ldp/graph/__init__.py
ldp/graph/async_torch.py
ldp/graph/common_ops.py
ldp/graph/gradient_estimators.py
ldp/graph/loss_ops.py
ldp/graph/memory.py
ldp/graph/op_utils.py
ldp/graph/ops.py
ldp/graph/torch_ops.py
ldp/graph/modules/__init__.py
ldp/graph/modules/llm_call.py
ldp/graph/modules/react.py
ldp/graph/modules/reflect.py
ldp/graph/modules/thought.py
ldp/llms/__init__.py
ldp/llms/prompts.py
ldp/nn/__init__.py
ldp/nn/lm_config.py
ldp/nn/utils.py
ldp/nn/agent/simple_local_agent.py
ldp/nn/chat_templates/README.md
ldp/nn/chat_templates/llama2_chat_template_ori.jinja
ldp/nn/chat_templates/llama3.1_chat_template_hf.jinja
ldp/nn/chat_templates/llama3.1_chat_template_nothought.jinja
ldp/nn/chat_templates/llama3.1_chat_template_thought.jinja
ldp/nn/chat_templates/llama3.1_chat_template_vllm.jinja
ldp/nn/chat_templates/llama3_chat_template_ori.jinja
ldp/nn/generation/__init__.py
ldp/nn/generation/base.py
ldp/nn/graph/llm_call_op.py
ldp/nn/handlers/chunking.py
ldp/nn/handlers/module_handler.py
ldp/nn/handlers/transformer_handler.py
ldp-0.43.0.dist-info/licenses/LICENSE
ldp-0.43.0.dist-info/METADATA
ldp-0.43.0.dist-info/WHEEL
ldp-0.43.0.dist-info/top_level.txt
ldp-0.43.0.dist-info/RECORD
