Metadata-Version: 2.4
Name: ldp
Version: 0.43.0
Summary: Agent framework for constructing language model agents and training on constructive tasks.
Author-email: FutureHouse technical staff <hello@futurehouse.org>
License:                                  Apache License
Project-URL: issues, https://github.com/Future-House/ldp/issues
Project-URL: repository, https://github.com/Future-House/ldp
Classifier: Intended Audience :: Developers
Classifier: License :: OSI Approved :: Apache Software License
Classifier: Operating System :: OS Independent
Classifier: Programming Language :: Python :: 3 :: Only
Classifier: Programming Language :: Python :: 3.11
Classifier: Programming Language :: Python :: 3.12
Classifier: Programming Language :: Python :: 3.13
Classifier: Programming Language :: Python
Classifier: Topic :: Scientific/Engineering :: Artificial Intelligence
Requires-Python: >=3.11
License-File: LICENSE
Requires-Dist: aiofiles
Requires-Dist: fhaviary>=0.32.0
Requires-Dist: fhlmi
Requires-Dist: httpx-aiohttp
Requires-Dist: numpy>=1.20
Requires-Dist: pydantic~=2.0
Requires-Dist: tenacity
Requires-Dist: tiktoken
Requires-Dist: tqdm
Requires-Dist: typing-extensions; python_version <= "3.11"
Provides-Extra: dev
Requires-Dist: fhaviary[xml]>=0.19; extra == "dev"
Requires-Dist: fhlmi[dev]; extra == "dev"
Requires-Dist: httpx; extra == "dev"
Requires-Dist: ipython>=8; extra == "dev"
Requires-Dist: ldp[monitor,nn,rich,server,typing,visualization]; extra == "dev"
Requires-Dist: litellm; extra == "dev"
Requires-Dist: mypy>=1.19; extra == "dev"
Requires-Dist: prek; extra == "dev"
Requires-Dist: pydantic~=2.9; extra == "dev"
Requires-Dist: pylint-pydantic; extra == "dev"
Requires-Dist: pylint>=3.2; extra == "dev"
Requires-Dist: pytest-asyncio; extra == "dev"
Requires-Dist: pytest-mock; extra == "dev"
Requires-Dist: pytest-recording; extra == "dev"
Requires-Dist: pytest-rerunfailures; extra == "dev"
Requires-Dist: pytest-subtests; extra == "dev"
Requires-Dist: pytest-sugar; extra == "dev"
Requires-Dist: pytest-timeout; extra == "dev"
Requires-Dist: pytest-timer[colorama]; extra == "dev"
Requires-Dist: pytest-xdist; extra == "dev"
Requires-Dist: pytest>=8; extra == "dev"
Requires-Dist: refurb>=2; extra == "dev"
Requires-Dist: usearch>=2.13; extra == "dev"
Requires-Dist: vcrpy>=8; extra == "dev"
Provides-Extra: monitor
Requires-Dist: wandb; extra == "monitor"
Provides-Extra: nn
Requires-Dist: accelerate; extra == "nn"
Requires-Dist: dask-cuda<25.10.0,>=24.8.2; extra == "nn"
Requires-Dist: dask-jobqueue; extra == "nn"
Requires-Dist: dask[distributed]; extra == "nn"
Requires-Dist: ldp[scg]; extra == "nn"
Requires-Dist: tokenizers>0.20; extra == "nn"
Requires-Dist: torch==2.6; extra == "nn"
Requires-Dist: transformers>=4.51; extra == "nn"
Requires-Dist: wandb; extra == "nn"
Provides-Extra: rich
Requires-Dist: rich; extra == "rich"
Requires-Dist: tqdm>=4.56; extra == "rich"
Provides-Extra: scg
Requires-Dist: dm-tree; extra == "scg"
Requires-Dist: networkx[default]~=3.4; extra == "scg"
Provides-Extra: server
Requires-Dist: fastapi>=0.109; extra == "server"
Provides-Extra: typing
Requires-Dist: httpx; extra == "typing"
Requires-Dist: types-aiofiles; extra == "typing"
Requires-Dist: types-tqdm; extra == "typing"
Provides-Extra: visualization
Requires-Dist: pydot>=3.0.1; extra == "visualization"
Dynamic: license-file
